mlvault/__init__.py
mlvault/config.py
mlvault/util.py
mlvault/api/__init__.py
mlvault/api/download.py
mlvault/api/upload.py
mlvault/cli/__init__.py
mlvault/cli/main.py
mlvault/cli/data/__init__.py
mlvault/cli/data/down.py
mlvault/cli/data/extract.py
mlvault/cli/data/main.py
mlvault/cli/data/pack.py
mlvault/cli/data/prepare.py
mlvault/cli/data/search.py
mlvault/cli/data/trash.py
mlvault/datapack/__init__.py
mlvault/datapack/main.py
mlvault-0.0.38.dist-info/METADATA
mlvault-0.0.38.dist-info/WHEEL
mlvault-0.0.38.dist-info/entry_points.txt
mlvault-0.0.38.dist-info/top_level.txt
mlvault-0.0.38.dist-info/RECORD
