Metadata-Version: 2.1
Name: mlvault
Version: 0.0.38
Author: MLVault
Classifier: Programming Language :: Python :: 3.10
Requires-Dist: huggingface-hub (>=0.19.4)
Requires-Dist: datasets (>=2.15.0)
Requires-Dist: Pillow
Requires-Dist: toml
